<?xml version="1.0" encoding="UTF-8" ?>
<odoo>
    <data>
    <record id="view_projet_form" model="ir.ui.view">
        <field name="name">projet.form</field>
        <field name="model">projet</field>
        <field name="arch" type="xml">
            <form string="Projet">
                <sheet>
                    <group>
                        <field name="name"/>
                        <field name="description"/>
                        <field name="date_debut"/>
                        <field name="date_fin"/>
                    </group>
                    <group>
                        <field name="stagiaire_id"/>
                    </group>
                </sheet>
            </form>
        </field>
    </record>

    <record id="view_projet_tree" model="ir.ui.view">
        <field name="name">projet.tree</field>
        <field name="model">projet</field>
        <field name="arch" type="xml">
            <tree string="Projets">
                <field name="name"/>
                <field name="date_debut"/>
                <field name="date_fin"/>
            </tree>
        </field>
    </record>

     <record id="action_projets" model="ir.actions.act_window">
        <field name="name">Projets</field>
        <field name="res_model">project.project</field>
        <field name="view_mode">tree,form</field>
     </record>
    </data>
</odoo>
